histogram_manipulation/__init__.py
histogram_manipulation/equalization.py
histogram_manipulation/matching.py
histogram_manipulation/stretching.py
histogram_manipulation-1.1.1.dist-info/LICENSE
histogram_manipulation-1.1.1.dist-info/METADATA
histogram_manipulation-1.1.1.dist-info/WHEEL
histogram_manipulation-1.1.1.dist-info/top_level.txt
histogram_manipulation-1.1.1.dist-info/RECORD
