Metadata-Version: 2.1
Name: histogram-manipulation
Version: 1.1.1
Summary: A library for histogram manipulation of images
Home-page: https://github.com/Black-Lights/hist_man.git
Author: Mohammad Ammar Mughees, Seyederfan Eshghollahi
Author-email: mohammadammar.mughees@mail.polimi.it, erfaneshghelahi@gmail.com
License: UNKNOWN
Platform: UNKNOWN
Classifier: Programming Language :: Python :: 3
Classifier: License :: OSI Approved :: MIT License
Classifier: Operating System :: OS Independent
Requires-Python: >=3.7
License-File: LICENSE
Requires-Dist: Jinja2>=3.1.4
Requires-Dist: Pillow>=11.0.0
Requires-Dist: PyQt5>=5.15.11
Requires-Dist: PyYAML>=6.0.2
Requires-Dist: affine>=2.4.0
Requires-Dist: anyio>=4.6.2
Requires-Dist: argon2-cffi>=23.1.0
Requires-Dist: attrs>=24.2.0
Requires-Dist: beautifulsoup4>=4.12.3
Requires-Dist: cffi>=1.17.1
Requires-Dist: charset-normalizer>=3.4.0
Requires-Dist: click>=8.1.7
Requires-Dist: cycler>=0.12.1
Requires-Dist: fonttools>=4.55.0
Requires-Dist: idna>=3.10
Requires-Dist: imageio>=2.36.0
Requires-Dist: kiwisolver>=1.4.7
Requires-Dist: matplotlib>=3.9.2
Requires-Dist: numpy>=2.1.3
Requires-Dist: opencv-python-headless>=4.10.0.84
Requires-Dist: opencv-python>=4.10.0
Requires-Dist: pandas>=2.2.3
Requires-Dist: rasterio>=1.4.2
Requires-Dist: requests>=2.32.3
Requires-Dist: scikit-image>=0.24.0
Requires-Dist: scipy>=1.14.1
Requires-Dist: soupsieve>=2.6
Requires-Dist: tifffile>=2024.9.20
Requires-Dist: urllib3>=2.2.3
